cli/__init__.py
cli/cli.py
cli/fingerprint.py
cli/lib.py
cli/commands/__init__.py
cli/commands/kafka_multiplugin_worker.py
sharemyai_plugins/__init__.py
sharemyai_pluginsv2/__init__.py
sharemyai_utils/__init__.py
sharemyai_utils/defaults.py
sharemyai_utils/gpt4all.py
sharemyai_utils/images.py
sharemyai_utils/run_v1.py
sharemyai_utils/run_v2.py
sharemyai_utils/utils.py
sharemyai_utils/videos.py
sharemyai_utils-0.2.7.dist-info/METADATA
sharemyai_utils-0.2.7.dist-info/WHEEL
sharemyai_utils-0.2.7.dist-info/entry_points.txt
sharemyai_utils-0.2.7.dist-info/top_level.txt
sharemyai_utils-0.2.7.dist-info/RECORD
